{"retrieved": "2016-12-31 23:38:45.384996", "children": [{"retrieved": "2016-12-31 23:38:45.384996", "children": [], "standard_slug": "5", "text": "CCSS.Math.Content.3.MD.C.5 Recognize area as an attribute of plane figures and understand concepts of area measurement."}, {"retrieved": "2016-12-31 23:38:45.384996", "children": [], "standard_slug": "6", "text": "CCSS.Math.Content.3.MD.C.6 Measure areas by counting unit squares (square cm, square m, square in, square ft, and improvised units)."}, {"retrieved": "2016-12-31 23:38:45.384996", "children": [], "standard_slug": "7", "text": "CCSS.Math.Content.3.MD.C.7 Relate area to the operations of multiplication and addition."}], "standard_slug": "C", "text": "C"}